{
	"id": "bHLpmrNr3p7GU1J",
	"json": "{\"id\":\"bHLpmrNr3p7GU1J\",\"url\":\"https://www.semanticscholar.org/author/R.-Nilforooshan/5195508\",\"uniqueKey\":\"https://www.semanticscholar.org/author/R.-Nilforooshan/5195508\",\"method\":\"GET\",\"noRetry\":false,\"retryCount\":0,\"errorMessages\":[],\"headers\":{},\"userData\":{\"__crawlee\":{\"enqueueStrategy\":\"same-hostname\"}}}",
	"method": "GET",
	"orderNo": 1732553251782,
	"retryCount": 0,
	"uniqueKey": "https://www.semanticscholar.org/author/R.-Nilforooshan/5195508",
	"url": "https://www.semanticscholar.org/author/R.-Nilforooshan/5195508"
}