{
	"id": "FhBL15CksNTXcH3",
	"json": "{\"id\":\"FhBL15CksNTXcH3\",\"url\":\"https://www.semanticscholar.org/author/S.-Auer/145044578\",\"uniqueKey\":\"https://www.semanticscholar.org/author/S.-Auer/145044578\",\"method\":\"GET\",\"noRetry\":false,\"retryCount\":0,\"errorMessages\":[],\"headers\":{},\"userData\":{\"__crawlee\":{\"enqueueStrategy\":\"same-hostname\"}}}",
	"method": "GET",
	"orderNo": 1732553234512,
	"retryCount": 0,
	"uniqueKey": "https://www.semanticscholar.org/author/S.-Auer/145044578",
	"url": "https://www.semanticscholar.org/author/S.-Auer/145044578"
}