{
	"id": "jEGKWB7p14V9Rdl",
	"json": "{\"id\":\"jEGKWB7p14V9Rdl\",\"url\":\"https://www.semanticscholar.org/author/Koichi-Ota/2000912578/citing-authors\",\"uniqueKey\":\"https://www.semanticscholar.org/author/Koichi-Ota/2000912578/citing-authors\",\"method\":\"GET\",\"noRetry\":false,\"retryCount\":0,\"errorMessages\":[],\"headers\":{},\"userData\":{\"__crawlee\":{\"enqueueStrategy\":\"same-hostname\"}}}",
	"method": "GET",
	"orderNo": 1732553257009,
	"retryCount": 0,
	"uniqueKey": "https://www.semanticscholar.org/author/Koichi-Ota/2000912578/citing-authors",
	"url": "https://www.semanticscholar.org/author/Koichi-Ota/2000912578/citing-authors"
}